LICENSE
MANIFEST.in
README.md
setup.py
auth/__init__.py
auth/middleware.py
auth/tests.py
auth/migrations/__init__.py
dashboard/__init__.py
dashboard/middleware.py
dashboard/settings.py
dashboard/urls.py
dashboard/wsgi.py
tsuru_autoscale/__init__.py
tsuru_autoscale/urls.py
tsuru_autoscale/version.py
tsuru_autoscale.egg-info/PKG-INFO
tsuru_autoscale.egg-info/SOURCES.txt
tsuru_autoscale.egg-info/dependency_links.txt
tsuru_autoscale.egg-info/requires.txt
tsuru_autoscale.egg-info/top_level.txt
tsuru_autoscale/action/__init__.py
tsuru_autoscale/action/client.py
tsuru_autoscale/action/forms.py
tsuru_autoscale/action/tests.py
tsuru_autoscale/action/urls.py
tsuru_autoscale/action/views.py
tsuru_autoscale/action/migrations/__init__.py
tsuru_autoscale/alarm/__init__.py
tsuru_autoscale/alarm/client.py
tsuru_autoscale/alarm/forms.py
tsuru_autoscale/alarm/tests.py
tsuru_autoscale/alarm/urls.py
tsuru_autoscale/alarm/views.py
tsuru_autoscale/alarm/migrations/__init__.py
tsuru_autoscale/app/__init__.py
tsuru_autoscale/app/tests.py
tsuru_autoscale/app/urls.py
tsuru_autoscale/app/views.py
tsuru_autoscale/datasource/__init__.py
tsuru_autoscale/datasource/client.py
tsuru_autoscale/datasource/forms.py
tsuru_autoscale/datasource/tests.py
tsuru_autoscale/datasource/urls.py
tsuru_autoscale/datasource/views.py
tsuru_autoscale/datasource/migrations/__init__.py
tsuru_autoscale/event/__init__.py
tsuru_autoscale/event/client.py
tsuru_autoscale/event/tests.py
tsuru_autoscale/event/views.py
tsuru_autoscale/event/migrations/__init__.py
tsuru_autoscale/instance/__init__.py
tsuru_autoscale/instance/client.py
tsuru_autoscale/instance/tests.py
tsuru_autoscale/instance/urls.py
tsuru_autoscale/instance/views.py
tsuru_autoscale/instance/migrations/__init__.py
tsuru_autoscale/native/__init__.py
tsuru_autoscale/native/forms.py
tsuru_autoscale/native/urls.py
tsuru_autoscale/native/views.py
tsuru_autoscale/static/autoscale/css/app.css
tsuru_autoscale/templates/action/get.html
tsuru_autoscale/templates/action/list.html
tsuru_autoscale/templates/action/new.html
tsuru_autoscale/templates/alarm/get.html
tsuru_autoscale/templates/alarm/list.html
tsuru_autoscale/templates/alarm/new.html
