Metadata-Version: 1.0
Name: tsuru-autoscale
Version: 0.5.0
Summary: Web dashboard for tsuru autoscale service
Home-page: https://github.com/tsuru/tsuru-autoscale-dashboard
Author: tsuru
Author-email: tsuru@corp.globo.com
License: UNKNOWN
Platform: UNKNOWN
